aitx/__init__.py
aitx/aitx.py
aitx/history.py
aitx/imagebox.py
aitx/lightbox.py
aitx-0.4.6.dist-info/LICENSE
aitx-0.4.6.dist-info/METADATA
aitx-0.4.6.dist-info/WHEEL
aitx-0.4.6.dist-info/top_level.txt
aitx-0.4.6.dist-info/RECORD
