Metadata-Version: 2.1
Name: aitx
Version: 0.4.6
Summary: The toolbox for general ML projects
Home-page: https://github.com/jeroyang/aitx
Author: Chia-Jung, Yang
Author-email: jeroyang@gmail.com
License: MIT
Keywords: aitx
Platform: UNKNOWN
Classifier: Development Status :: 2 - Pre-Alpha
Classifier: Intended Audience :: Developers
Classifier: License :: OSI Approved :: BSD License
Classifier: Natural Language :: English
Classifier: Programming Language :: Python :: 3.5
Classifier: Programming Language :: Python :: 3.6
